mxmul_pkg/__init__.py
mxmul_pkg/tommytime.py
tommy_time-0.1.0.dist-info/LICENSE
tommy_time-0.1.0.dist-info/METADATA
tommy_time-0.1.0.dist-info/WHEEL
tommy_time-0.1.0.dist-info/top_level.txt
tommy_time-0.1.0.dist-info/RECORD
