Metadata-Version: 2.1
Name: tommy-time
Version: 0.1.0
Summary: # Tommy的时间！
